Metadata-Version: 2.1
Name: soda-core-vertica
Version: 3.5.6
License-File: LICENSE
Requires-Dist: soda-core==3.5.6
Requires-Dist: vertica-python<2.0,>=1.0.3
